wireframe_it/__init__.py
wireframe_it/__main__.py
wireframe_it/cli.py
wireframe_it/core.py
wireframe_it/screenshot.py
wireframe_it/placeholders/placeholder.jpg
wireframe_it/placeholders/placeholder.png
wireframe_it/placeholders/placeholder.svg
wireframe_it-0.1.1.dist-info/METADATA
wireframe_it-0.1.1.dist-info/WHEEL
wireframe_it-0.1.1.dist-info/entry_points.txt
wireframe_it-0.1.1.dist-info/licenses/LICENSE
wireframe_it-0.1.1.dist-info/RECORD
