Metadata-Version: 2.4
Name: wireframe-it
Version: 0.1.1
Summary: Convert live web pages to wireframe placeholders and screenshots
Author: mr-eggleton
License: MIT License
License-File: LICENSE
Requires-Python: >=3.9
Requires-Dist: beautifulsoup4>=4.12
Requires-Dist: playwright>=1.39
Requires-Dist: requests>=2.31
Requires-Dist: typer>=0.12
Provides-Extra: all
Requires-Dist: lxml>=4.9; extra == 'all'
Provides-Extra: dev
Requires-Dist: pytest>=7.4; extra == 'dev'
Requires-Dist: python-dotenv>=1.0; extra == 'dev'
